kos_sdk/__init__.py
kos_sdk/py.typed
kos_sdk/requirements-dev.txt
kos_sdk/requirements.txt
kos_sdk/algorithms/zmp.py
kos_sdk/locomotion/ppo.py
kos_sdk/manipulatoin/act.py
kos_sdk/setup/calibrate_imu.py
kos_sdk/setup/calibrate_servos.py
kos_sdk/tests/test_camera.py
kos_sdk/tests/test_connection.py
kos_sdk/tests/test_imu.py
kos_sdk/tests/test_led.py
kos_sdk/tests/test_microphone.py
kos_sdk/tests/test_servos.py
kos_sdk/tests/test_speaker.py
kos_sdk/tools/keyboard_tk.py
kos_sdk/tools/play_skill.py
kos_sdk/tools/record_skill.py
kos_sdk/tools/skills_data.py
kos_sdk/utils/robot.py
kos_sdk/utils/telemetry.py
kos_sdk/utils/unit_types.py
kos_sdk-0.0.1.dist-info/LICENSE
kos_sdk-0.0.1.dist-info/METADATA
kos_sdk-0.0.1.dist-info/WHEEL
kos_sdk-0.0.1.dist-info/top_level.txt
kos_sdk-0.0.1.dist-info/RECORD
