Metadata-Version: 2.2
Name: kos-sdk
Version: 0.0.1
Summary: Software Development Kit for KOS
Home-page: https://github.com/kscalelabs/kos-sdk
Author: Jingxiang Mo
Requires-Python: >=3.11
License-File: LICENSE
Requires-Dist: colorlogging
Requires-Dist: kscale
Requires-Dist: matplotlib
Requires-Dist: mujoco
Requires-Dist: onnxruntime
Requires-Dist: pybullet
Requires-Dist: pykos
Requires-Dist: aiortc
Requires-Dist: opencv-python
Requires-Dist: numpy
Requires-Dist: requests
Requires-Dist: ultralytics
Requires-Dist: av
Requires-Dist: kos-sim
Provides-Extra: dev
Requires-Dist: black; extra == "dev"
Requires-Dist: darglint; extra == "dev"
Requires-Dist: mypy; extra == "dev"
Requires-Dist: pytest; extra == "dev"
Requires-Dist: ruff; extra == "dev"
Dynamic: author
Dynamic: description
Dynamic: description-content-type
Dynamic: home-page
Dynamic: provides-extra
Dynamic: requires-dist
Dynamic: requires-python
Dynamic: summary
